cr/__init__.py
crcli/__init__.py
crcli/scripts/__init__.py
crcli/scripts/cli.py
crcli/scripts/dump.py
crcli-0.0.1.dist-info/DESCRIPTION.rst
crcli-0.0.1.dist-info/METADATA
crcli-0.0.1.dist-info/RECORD
crcli-0.0.1.dist-info/WHEEL
crcli-0.0.1.dist-info/entry_points.txt
crcli-0.0.1.dist-info/metadata.json
crcli-0.0.1.dist-info/top_level.txt
